model/__init__.py
model/load.py
model/main.py
model/model.py
numberAI-0.0.1.dist-info/LICENCE.txt
numberAI-0.0.1.dist-info/METADATA
numberAI-0.0.1.dist-info/WHEEL
numberAI-0.0.1.dist-info/top_level.txt
numberAI-0.0.1.dist-info/RECORD
